Workbook

Sheet Summary
A1: SmartPlaze — manual test plan
A2: Staging: https://smartplaze.com · Generated 2026-09-24 · Fill the blue cells on the Scenarios sheet (Status, Actual result, Tester / date).
A4: Legend
A5: Success | B5: Happy path: the step must work as described.
A6: Failure (expected error) | B6: The app must refuse or block the action with the described message; a refusal is a PASS.
A7: Blocked (needs provider key) | B7: Cannot be run until the named key is configured (K-Pay live keys, Google redirect URI).
A8: Status values | B8: Pass / Fail / Blocked / Not run — dropdown on the Scenarios sheet.
A11: Area | B11: Scenarios | C11: Success paths | D11: Expected failures | E11: Blocked (keys) | F11: Pass | G11: Fail | H11: Not run
A12: Storefront | B12: =COUNTIF(Scenarios!$B$2:$B$120,A12) | C12: =COUNTIFS(Scenarios!$B$2:$B$120,A12,Scenarios!$H$2:$H$120,"Success") | D12: =COUNTIFS(Scenarios!$B$2:$B$120,A12,Scenarios!$H$2:$H$120,"Failure*") | E12: =COUNTIFS(Scenarios!$B$2:$B$120,A12,Scenarios!$H$2:$H$120,"Blocked*") | F12: =COUNTIFS(Scenarios!$B$2:$B$120,A12,Scenarios!$J$2:$J$120,"Pass") | G12: =COUNTIFS(Scenarios!$B$2:$B$120,A12,Scenarios!$J$2:$J$120,"Fail") | H12: =B12-F12-G12-COUNTIFS(Scenarios!$B$2:$B$120,A12,Scenarios!$J$2:$J$120,"Blocked")
A13: Flash deals | B13: =COUNTIF(Scenarios!$B$2:$B$120,A13) | C13: =COUNTIFS(Scenarios!$B$2:$B$120,A13,Scenarios!$H$2:$H$120,"Success") | D13: =COUNTIFS(Scenarios!$B$2:$B$120,A13,Scenarios!$H$2:$H$120,"Failure*") | E13: =COUNTIFS(Scenarios!$B$2:$B$120,A13,Scenarios!$H$2:$H$120,"Blocked*") | F13: =COUNTIFS(Scenarios!$B$2:$B$120,A13,Scenarios!$J$2:$J$120,"Pass") | G13: =COUNTIFS(Scenarios!$B$2:$B$120,A13,Scenarios!$J$2:$J$120,"Fail") | H13: =B13-F13-G13-COUNTIFS(Scenarios!$B$2:$B$120,A13,Scenarios!$J$2:$J$120,"Blocked")
A14: Authentication | B14: =COUNTIF(Scenarios!$B$2:$B$120,A14) | C14: =COUNTIFS(Scenarios!$B$2:$B$120,A14,Scenarios!$H$2:$H$120,"Success") | D14: =COUNTIFS(Scenarios!$B$2:$B$120,A14,Scenarios!$H$2:$H$120,"Failure*") | E14: =COUNTIFS(Scenarios!$B$2:$B$120,A14,Scenarios!$H$2:$H$120,"Blocked*") | F14: =COUNTIFS(Scenarios!$B$2:$B$120,A14,Scenarios!$J$2:$J$120,"Pass") | G14: =COUNTIFS(Scenarios!$B$2:$B$120,A14,Scenarios!$J$2:$J$120,"Fail") | H14: =B14-F14-G14-COUNTIFS(Scenarios!$B$2:$B$120,A14,Scenarios!$J$2:$J$120,"Blocked")
A15: Cart & checkout | B15: =COUNTIF(Scenarios!$B$2:$B$120,A15) | C15: =COUNTIFS(Scenarios!$B$2:$B$120,A15,Scenarios!$H$2:$H$120,"Success") | D15: =COUNTIFS(Scenarios!$B$2:$B$120,A15,Scenarios!$H$2:$H$120,"Failure*") | E15: =COUNTIFS(Scenarios!$B$2:$B$120,A15,Scenarios!$H$2:$H$120,"Blocked*") | F15: =COUNTIFS(Scenarios!$B$2:$B$120,A15,Scenarios!$J$2:$J$120,"Pass") | G15: =COUNTIFS(Scenarios!$B$2:$B$120,A15,Scenarios!$J$2:$J$120,"Fail") | H15: =B15-F15-G15-COUNTIFS(Scenarios!$B$2:$B$120,A15,Scenarios!$J$2:$J$120,"Blocked")
A16: Orders (buyer) | B16: =COUNTIF(Scenarios!$B$2:$B$120,A16) | C16: =COUNTIFS(Scenarios!$B$2:$B$120,A16,Scenarios!$H$2:$H$120,"Success") | D16: =COUNTIFS(Scenarios!$B$2:$B$120,A16,Scenarios!$H$2:$H$120,"Failure*") | E16: =COUNTIFS(Scenarios!$B$2:$B$120,A16,Scenarios!$H$2:$H$120,"Blocked*") | F16: =COUNTIFS(Scenarios!$B$2:$B$120,A16,Scenarios!$J$2:$J$120,"Pass") | G16: =COUNTIFS(Scenarios!$B$2:$B$120,A16,Scenarios!$J$2:$J$120,"Fail") | H16: =B16-F16-G16-COUNTIFS(Scenarios!$B$2:$B$120,A16,Scenarios!$J$2:$J$120,"Blocked")
A17: Seller area | B17: =COUNTIF(Scenarios!$B$2:$B$120,A17) | C17: =COUNTIFS(Scenarios!$B$2:$B$120,A17,Scenarios!$H$2:$H$120,"Success") | D17: =COUNTIFS(Scenarios!$B$2:$B$120,A17,Scenarios!$H$2:$H$120,"Failure*") | E17: =COUNTIFS(Scenarios!$B$2:$B$120,A17,Scenarios!$H$2:$H$120,"Blocked*") | F17: =COUNTIFS(Scenarios!$B$2:$B$120,A17,Scenarios!$J$2:$J$120,"Pass") | G17: =COUNTIFS(Scenarios!$B$2:$B$120,A17,Scenarios!$J$2:$J$120,"Fail") | H17: =B17-F17-G17-COUNTIFS(Scenarios!$B$2:$B$120,A17,Scenarios!$J$2:$J$120,"Blocked")
A18: Back-office | B18: =COUNTIF(Scenarios!$B$2:$B$120,A18) | C18: =COUNTIFS(Scenarios!$B$2:$B$120,A18,Scenarios!$H$2:$H$120,"Success") | D18: =COUNTIFS(Scenarios!$B$2:$B$120,A18,Scenarios!$H$2:$H$120,"Failure*") | E18: =COUNTIFS(Scenarios!$B$2:$B$120,A18,Scenarios!$H$2:$H$120,"Blocked*") | F18: =COUNTIFS(Scenarios!$B$2:$B$120,A18,Scenarios!$J$2:$J$120,"Pass") | G18: =COUNTIFS(Scenarios!$B$2:$B$120,A18,Scenarios!$J$2:$J$120,"Fail") | H18: =B18-F18-G18-COUNTIFS(Scenarios!$B$2:$B$120,A18,Scenarios!$J$2:$J$120,"Blocked")
A19: API & security | B19: =COUNTIF(Scenarios!$B$2:$B$120,A19) | C19: =COUNTIFS(Scenarios!$B$2:$B$120,A19,Scenarios!$H$2:$H$120,"Success") | D19: =COUNTIFS(Scenarios!$B$2:$B$120,A19,Scenarios!$H$2:$H$120,"Failure*") | E19: =COUNTIFS(Scenarios!$B$2:$B$120,A19,Scenarios!$H$2:$H$120,"Blocked*") | F19: =COUNTIFS(Scenarios!$B$2:$B$120,A19,Scenarios!$J$2:$J$120,"Pass") | G19: =COUNTIFS(Scenarios!$B$2:$B$120,A19,Scenarios!$J$2:$J$120,"Fail") | H19: =B19-F19-G19-COUNTIFS(Scenarios!$B$2:$B$120,A19,Scenarios!$J$2:$J$120,"Blocked")
A20: Operations | B20: =COUNTIF(Scenarios!$B$2:$B$120,A20) | C20: =COUNTIFS(Scenarios!$B$2:$B$120,A20,Scenarios!$H$2:$H$120,"Success") | D20: =COUNTIFS(Scenarios!$B$2:$B$120,A20,Scenarios!$H$2:$H$120,"Failure*") | E20: =COUNTIFS(Scenarios!$B$2:$B$120,A20,Scenarios!$H$2:$H$120,"Blocked*") | F20: =COUNTIFS(Scenarios!$B$2:$B$120,A20,Scenarios!$J$2:$J$120,"Pass") | G20: =COUNTIFS(Scenarios!$B$2:$B$120,A20,Scenarios!$J$2:$J$120,"Fail") | H20: =B20-F20-G20-COUNTIFS(Scenarios!$B$2:$B$120,A20,Scenarios!$J$2:$J$120,"Blocked")
A21: Total | B21: =SUM(B12:B20) | C21: =SUM(C12:C20) | D21: =SUM(D12:D20) | E21: =SUM(E12:E20) | F21: =SUM(F12:F20) | G21: =SUM(G12:G20) | H21: =SUM(H12:H20)
A23: Progress | B23: =IF(B21=0,0,(F21+G21)/B21) | C23: of scenarios executed (Pass + Fail).
A24: Pass rate | B24: =IF(F21+G21=0,0,F21/(F21+G21)) | C24: Pass ÷ executed. Counts update automatically from the Scenarios sheet.

Sheet Scenarios
A1: ID | B1: Area | C1: Scenario | D1: Preconditions | E1: Steps | F1: Test data | G1: Expected result | H1: Expected outcome | I1: Priority | J1: Status | K1: Actual result | L1: Tester / date
A2: STF-01 | B2: Storefront | C2: Home page renders the Jumia-style layout | D2: None | E2: 1. Open the home page on desktop (≥1280 px). | F2: — | G2: Navy header with search + category select; left sidebar with the 11 departments; 4-slide hero with escrow panel; category circles; Flash Deals block with countdown; trust strip; Top Categories / Newest / Featured Stores panels; 15-product showcase; escrow walkthrough; footer. | H2: Success | I2: High | J2: Pass | K2: Example: all sections rendered on Chrome 130 desktop, staging. | L2: G. Awah 2026-09-24
A3: STF-02 | B3: Storefront | C3: Hero carousel controls | D3: Home page open | E3: 1. Wait 7 s. 2. Click the right/left arrows. 3. Click a dot. 4. Focus the hero and press ← →. 5. Hover the hero. | F3: — | G3: Slides auto-advance every ~6.5 s; arrows, dots and keyboard change slides; autoplay pauses while hovering. | H3: Success | I3: Medium
A4: STF-03 | B4: Storefront | C4: Language switch with flags | D4: None | E4: 1. Click the French flag in the header. 2. Browse home, a category, a product, the login page. 3. Switch back with the UK flag. | F4: — | G4: URL becomes /fr/…; every visible text is French (header, sidebar, buttons, footer); switching back restores English at the same page. | H4: Success | I4: High
A5: STF-04 | B5: Storefront | C5: Dark mode | D5: None | E5: 1. Click the moon/sun toggle. 2. Reload. 3. Open the deals page. | F5: — | G5: Whole site switches theme, choice persists after reload, headings and prices stay readable on dark backgrounds. | H5: Success | I5: Medium
A6: STF-05 | B6: Storefront | C6: Mobile layout | D6: Phone or browser at 375 px | E6: 1. Open home. 2. Scroll every section. 3. Swipe the category and deal rails. 4. Check the bottom bar. | F6: — | G6: White two-row header (menu, logo, flag, bell, wishlist, cart + search field); rails scroll horizontally; fixed bottom bar with Home / Categories / Deals / Wishlist / Account; no horizontal page scroll; chat button sits above the bar. | H6: Success | I6: High
A7: STF-06 | B7: Storefront | C7: Bottom bar Account while logged out | D7: Logged out, mobile | E7: 1. Tap Account in the bottom bar. | F7: — | G7: Login page opens. | H7: Success | I7: Low
A8: STF-07 | B8: Storefront | C8: Search suggestions appear instantly | D8: None | E8: 1. Click the header search. 2. Type "sofa". 3. Wait half a second. | F8: sofa | G8: Dropdown shows "Search for “sofa”", up to 5 products with thumbnail/category/price (matching text in bold), the Modern Sofas category with its parent, and matching stores. | H8: Success | I8: High
A9: STF-08 | B9: Storefront | C9: Suggestions need two characters | D9: None | E9: 1. Type a single letter in the search. | F9: s | G9: No dropdown rows besides recent searches; nothing is fetched. | H9: Failure (expected error) | I9: Low
A10: STF-09 | B10: Storefront | C10: Keyboard navigation in suggestions | D10: Dropdown open with results | E10: 1. Press ↓ twice. 2. Press Enter. | F10: sofa | G10: Second row (first product) highlights; Enter opens that product page. | H10: Success | I10: Medium
A11: STF-10 | B11: Storefront | C11: Search with no matches | D11: None | E11: 1. Type "zzzzqq". 2. Press Enter. | F11: zzzzqq | G11: Dropdown says no matches; Enter opens /search with the empty-results message. | H11: Failure (expected error) | I11: Low
A12: STF-11 | B12: Storefront | C12: Search results page and category filter | D12: None | E12: 1. Choose "Fashion" in the header select. 2. Type "dress". 3. Submit. | F12: dress + Fashion | G12: /search?q=dress&category=fashion lists only fashion listings; stores tab lists matching stores. | H12: Success | I12: Medium
A13: STF-12 | B13: Storefront | C13: Recent searches | D13: One search already made | E13: 1. Focus the empty search box. 2. Click Clear. | F13: — | G13: Recent terms listed with a clock icon; Clear empties the list (stored per browser only). | H13: Success | I13: Low
A14: STF-13 | B14: Storefront | C14: Category page with sub-categories | D14: None | E14: 1. Open Frames & Wall Art. 2. Click a sub-category chip. 3. Use the sort and condition filters. | F14: /categories/frames-wall-art | G14: Root page shows listings of all five sub-categories; chip narrows to one; filters and pagination work. | H14: Success | I14: High
... A120: CHK-19 | B120: Cart & checkout | C120: Group page and order detail stay consistent | D120: A member cart order exists | E120: 1. Open My orders and click the "SM-XXXXXX · N items" chip. 2. Click "View details" on one line. 3. Confirm receipt on that line and return to the group page. | F120: — | G120: The group page (/account/orders/group/<id>) lists every line with status pills and per-line actions; the single-order page shows the same chip; the updated status is reflected on both pages. | H120: Success | I120: Medium

Sheet Accounts & setup
A1: Test accounts (staging)
A3: Role | B3: Email | C3: Password | D3: What it can do
A4: Super admin | B4: test@smartmarket.dev | C4: NewPassword456 | D4: Everything, incl. roles, jobs, money actions
A5: Accountant | B5: accountant@smartmarket.dev | C5: Account123 | D5: Payments, withdrawals, escrow release/refund; no operations
A6: Customer service | B6: cs@smartmarket.dev | C6: Service123 | D6: Users, stores, listings, categories, plans, disputes, flash campaigns; no money
A7: Buyer | B7: buyer@smartmarket.dev | C7: BuyerPass123 | D7: Customer without a store
A8: Seller (Smart Trust) | B8: smarttrust@smartmarket.dev | C8: SmartTrust2026! | D8: Owns the Smart Trust store (Premium plan, 96 listings)
A9: Seller (demo) | B9: tech.elite@smartmarket.dev | C9: Seller123! | D9: Demo store Tech Elite (all demo sellers use Seller123!)
A11: Environment notes
A12: Staging URL | B12: https://smartplaze.com (French: /fr)
A13: Admin back-office | B13: https://smartplaze.com/admin
A14: Seller area | B14: https://smartplaze.com/seller
A15: Email OTP | B15: RESEND_API_KEY is not set yet: registration and password-reset emails are not delivered. Use the accounts above; scenarios marked Blocked depend on it.
A16: Mobile Money | B16: K-Pay keys answer "platform in maintenance" until the merchant account is live: Mobile Money checkout, subscription purchase, refunds and payouts are Blocked; cash on delivery works.
A17: Google sign-in | B17: Add https://api.smartplaze.com/api/auth/google/callback as an authorised redirect URI in Google Cloud Console before testing.
A18: Assistant | B18: GEMINI_API_KEY set on the server (same key and model as ELIZFLOW). Without it, the chat answers in built-in mode.
A19: Flash campaigns | B19: Create them in Back-office → Flash deals. The flash-campaigns job applies/restores prices every 30 seconds; the storefront cache refreshes within 20 seconds.
A20: Demo data | B20: 7 demo stores and 51 demo listings (sellers use Seller123!) sit next to the Smart Trust store; purge before launch.
A21: Reset a scenario | B21: Cancelling a campaign restores prices; archiving a listing frees quota; an admin can suspend/reactivate stores and users freely on staging.
